LICENSE
MANIFEST.in
README.md
requirements.txt
setup.py
transfertools/__init__.py
transfertools/version.py
transfertools.egg-info/PKG-INFO
transfertools.egg-info/SOURCES.txt
transfertools.egg-info/dependency_links.txt
transfertools.egg-info/requires.txt
transfertools.egg-info/top_level.txt
transfertools/models/__init__.py
transfertools/models/base.py
transfertools/models/cbit.py
transfertools/models/coral.py
transfertools/models/locit.py
transfertools/models/tca.py
transfertools/utils/__init__.py
transfertools/utils/preprocessing.py
transfertools/utils/utils.py