Metadata-Version: 2.1
Name: transfertools
Version: 0.1.2
Summary: A compact Python toolbox for transfer learning.
Home-page: https://github.com/Vincent-Vercruyssen/transfertools
Author: Vincent Vercruyssen
Author-email: V.Vercruyssen@gmail.com
License: UNKNOWN
Keywords: transfer learning,anomaly detection,domain adaptation,instance weighting
Platform: UNKNOWN
Classifier: Intended Audience :: Science/Research
Classifier: License :: OSI Approved :: Apache Software License
Classifier: Topic :: Scientific/Engineering :: Artificial Intelligence
Classifier: Programming Language :: Python :: 3
